strictstore/__init__.py
strictstore/exceptions.py
strictstore/store.py
strictstore-0.1.0.dist-info/licenses/LICENSE
strictstore-0.1.0.dist-info/METADATA
strictstore-0.1.0.dist-info/WHEEL
strictstore-0.1.0.dist-info/top_level.txt
strictstore-0.1.0.dist-info/RECORD
