Metadata-Version: 2.4
Name: strictstore
Version: 0.1.0
Summary: Strict global store with class ownership
Author: Lokesh52324
License-File: LICENSE
Dynamic: license-file
